tinyrl/__init__.py
tinyrl/external/rl_tools/include/rl_tools/containers.h
tinyrl/external/rl_tools/include/rl_tools/rl_tools.h
tinyrl/external/rl_tools/include/rl_tools/version.h
tinyrl/external/rl_tools/include/rl_tools/containers/operations_arm.h
tinyrl/external/rl_tools/include/rl_tools/containers/operations_cpu.h
tinyrl/external/rl_tools/include/rl_tools/containers/operations_cpu_blas.h
tinyrl/external/rl_tools/include/rl_tools/containers/operations_cpu_mkl.h
tinyrl/external/rl_tools/include/rl_tools/containers/operations_cpu_openblas.h
tinyrl/external/rl_tools/include/rl_tools/containers/operations_cuda.h
tinyrl/external/rl_tools/include/rl_tools/containers/operations_dummy.h
tinyrl/external/rl_tools/include/rl_tools/containers/operations_esp32.h
tinyrl/external/rl_tools/include/rl_tools/containers/operations_generic.h
tinyrl/external/rl_tools/include/rl_tools/containers/persist.h
tinyrl/external/rl_tools/include/rl_tools/containers/persist_code.h
tinyrl/external/rl_tools/include/rl_tools/devices/arm.h
tinyrl/external/rl_tools/include/rl_tools/devices/cpu.h
tinyrl/external/rl_tools/include/rl_tools/devices/cpu_accelerate.h
tinyrl/external/rl_tools/include/rl_tools/devices/cpu_blas.h
tinyrl/external/rl_tools/include/rl_tools/devices/cpu_mkl.h
tinyrl/external/rl_tools/include/rl_tools/devices/cpu_openblas.h
tinyrl/external/rl_tools/include/rl_tools/devices/cpu_tensorboard.h
tinyrl/external/rl_tools/include/rl_tools/devices/cuda.h
tinyrl/external/rl_tools/include/rl_tools/devices/devices.h
tinyrl/external/rl_tools/include/rl_tools/devices/dummy.h
tinyrl/external/rl_tools/include/rl_tools/devices/esp32.h
tinyrl/external/rl_tools/include/rl_tools/devices/generic.h
tinyrl/external/rl_tools/include/rl_tools/logging/operations_arduino.h
tinyrl/external/rl_tools/include/rl_tools/logging/operations_arm.h
tinyrl/external/rl_tools/include/rl_tools/logging/operations_cpu.h
tinyrl/external/rl_tools/include/rl_tools/logging/operations_cpu_tensorboard.h
tinyrl-0.4.3.dist-info/METADATA
tinyrl-0.4.3.dist-info/WHEEL
tinyrl-0.4.3.dist-info/licenses/LICENSE
tinyrl-0.4.3.dist-info/RECORD
